[
    {
        "name": "Oberon Dynamics",
        "coordinates": "50.1025,8.6299",
        "description": "Innovative German engineering firm specializing in high-performance laptops for the corporate and creative sectors",
        "insights": "Police Insights & Corporate Espionage Gossip: Rumors circulating suggest possible data breaches and internal conflicts within some major tech companies.",
        "image": "https://upload.wikimedia.org/wikipedia/commons/a/ac/Frankfurt_Main_August_2020_1.jpg"
    }
]